mongodb_python_manager/__init__.py
mongodb_python_manager/main.py
mongodb_python_manager-2.0.1.dist-info/LICENSE
mongodb_python_manager-2.0.1.dist-info/METADATA
mongodb_python_manager-2.0.1.dist-info/WHEEL
mongodb_python_manager-2.0.1.dist-info/RECORD
