Metadata-Version: 2.1
Name: mongodb-python-manager
Version: 2.0.1
Summary: 
Author: ldom
Author-email: louis@giron-dom.eu
Requires-Python: >=3.9,<3.13
Classifier: Programming Language :: Python :: 3
Classifier: Programming Language :: Python :: 3.9
Classifier: Programming Language :: Python :: 3.10
Classifier: Programming Language :: Python :: 3.11
Requires-Dist: dnspython (>=2.4.2,<3.0.0)
Requires-Dist: exceptiongroup (>=1.1.3,<2.0.0)
Requires-Dist: pandas (>=2.1.1,<3.0.0)
Requires-Dist: pymongo (>=4.5.0,<5.0.0)
Requires-Dist: python-dotenv (>=1.0.0,<2.0.0)
Requires-Dist: structlog (>=23.1.0,<24.0.0)
Requires-Dist: tqdm (>=4.66.1,<5.0.0)
